package_helper_test_2022_01_18_17h12/__init__.py
package_helper_test_2022_01_18_17h12/package_helper_test_2022_01_18_17h12.py
package_helper_test_2022_01_18_17h12/sub_package_1/__init__.py
package_helper_test_2022_01_18_17h12/sub_package_1/my_class_1.py
package_helper_test_2022_01_18_17h12/sub_package_2/__init__.py
package_helper_test_2022_01_18_17h12/sub_package_2/my_class_2.py
package_helper_test_2022_01_18_17h12/sub_package_2/my_class_3.py
tests/__init__.py
tests/test_package_helper_test_2022_01_18_17h12.py
package_helper_test_2022_01_18_17h12-0.1.0.dist-info/AUTHORS.rst
package_helper_test_2022_01_18_17h12-0.1.0.dist-info/LICENSE
package_helper_test_2022_01_18_17h12-0.1.0.dist-info/METADATA
package_helper_test_2022_01_18_17h12-0.1.0.dist-info/WHEEL
package_helper_test_2022_01_18_17h12-0.1.0.dist-info/top_level.txt
package_helper_test_2022_01_18_17h12-0.1.0.dist-info/RECORD
