Metadata-Version: 2.1
Name: package-helper-test-2022-01-18-17h12
Version: 0.1.0
Summary: This is a test of Package Helper 2.
Home-page: https://github.com/francois-durand/package_helper_test_2022_01_18_17h12
Author: François Durand
Author-email: fradurand@gmail.com
License: GNU General Public License v3
Keywords: package_helper_test_2022_01_18_17h12
Platform: UNKNOWN
Classifier: Development Status :: 2 - Pre-Alpha
Classifier: Intended Audience :: Developers
Classifier: License :: OSI Approved :: GNU General Public License v3 (GPLv3)
Classifier: Natural Language :: English
Classifier: Programming Language :: Python :: 3
Classifier: Programming Language :: Python :: 3.6
Classifier: Programming Language :: Python :: 3.7
Classifier: Programming Language :: Python :: 3.8
Requires-Python: >=3.6
License-File: LICENSE
License-File: AUTHORS.rst
